speechshift/__init__.py
speechshift/cli.py
speechshift/main.py
speechshift/core/__init__.py
speechshift/core/audio_recorder.py
speechshift/core/audio_transcriber.py
speechshift/core/config.py
speechshift/core/logger.py
speechshift/core/notification_manager.py
speechshift/core/speechshift_daemon.py
speechshift/core/wayland_text_input.py
speechshift-0.1.4.dist-info/METADATA
speechshift-0.1.4.dist-info/WHEEL
speechshift-0.1.4.dist-info/entry_points.txt
speechshift-0.1.4.dist-info/licenses/LICENSE
speechshift-0.1.4.dist-info/RECORD
