Metadata-Version: 2.4
Name: speechshift
Version: 0.1.4
Summary: A fully local, offline first speech-to-text application made for Linux.
Project-URL: Homepage, https://github.com/bharatkalluri/speechshift
Project-URL: Repository, https://github.com/bharatkalluri/speechshift.git
Project-URL: Issues, https://github.com/bharatkalluri/speechshift/issues
Author-email: Bharat Kalluri <kalluribharat@gmail.com>
License: MIT
License-File: LICENSE
Keywords: audio,hyprland,speech-to-text,transcription,wayland
Classifier: Development Status :: 4 - Beta
Classifier: Environment :: X11 Applications :: Qt
Classifier: Intended Audience :: End Users/Desktop
Classifier: License :: OSI Approved :: MIT License
Classifier: Operating System :: POSIX :: Linux
Classifier: Programming Language :: Python :: 3
Classifier: Programming Language :: Python :: 3.8
Classifier: Programming Language :: Python :: 3.9
Classifier: Programming Language :: Python :: 3.10
Classifier: Programming Language :: Python :: 3.11
Classifier: Programming Language :: Python :: 3.12
Classifier: Topic :: Desktop Environment
Classifier: Topic :: Multimedia :: Sound/Audio :: Speech
Requires-Python: >=3.8
Requires-Dist: assemblyai>=0.17.0
Requires-Dist: black>=24.8.0
Requires-Dist: faster-whisper>=0.10.0
Requires-Dist: librosa>=0.10.0
Requires-Dist: numpy>=1.21.0
Requires-Dist: psutil>=7.1.0
Requires-Dist: sounddevice>=0.4.6
Requires-Dist: soundfile>=0.12.0
